MANIFEST.in
README.md
setup.py
src/vdk/plugin/impala/impala_configuration.py
src/vdk/plugin/impala/impala_connection.py
src/vdk/plugin/impala/impala_error_classifier.py
src/vdk/plugin/impala/impala_error_handler.py
src/vdk/plugin/impala/impala_helper.py
src/vdk/plugin/impala/impala_lineage_plugin.py
src/vdk/plugin/impala/impala_plugin.py
src/vdk/plugin/impala/templates/__init__.py
src/vdk/plugin/impala/templates/data_quality_exception.py
src/vdk/plugin/impala/templates/template_arguments_validator.py
src/vdk/plugin/impala/templates/utility.py
src/vdk/plugin/impala/templates/load/__init__.py
src/vdk/plugin/impala/templates/load/dimension/__init__.py
src/vdk/plugin/impala/templates/load/dimension/scd1/00-dimension-scd1-definition.py
src/vdk/plugin/impala/templates/load/dimension/scd1/01-test-if-view-matches-target.sql
src/vdk/plugin/impala/templates/load/dimension/scd1/02-handle-quality-checks.py
src/vdk/plugin/impala/templates/load/dimension/scd1/03-refresh.sql
src/vdk/plugin/impala/templates/load/dimension/scd1/04-compute-stats.sql
src/vdk/plugin/impala/templates/load/dimension/scd1/__init__.py
src/vdk/plugin/impala/templates/load/dimension/scd1/02-requisite-sql-scripts/02-insert-into-target.sql
src/vdk/plugin/impala/templates/load/dimension/scd2/00-dimension-scd2-definition.py
src/vdk/plugin/impala/templates/load/dimension/scd2/01-test-if-view-matches-target.sql
src/vdk/plugin/impala/templates/load/dimension/scd2/02-insert-into-target.sql
src/vdk/plugin/impala/templates/load/dimension/scd2/03-refresh.sql
src/vdk/plugin/impala/templates/load/dimension/scd2/04-compute-stats.sql
src/vdk/plugin/impala/templates/load/dimension/scd2/__init__.py
src/vdk/plugin/impala/templates/load/fact/__init__.py
src/vdk/plugin/impala/templates/load/fact/insert/00-fact-snapshot-definition.py
src/vdk/plugin/impala/templates/load/fact/insert/01-test-if-view-matches-target.sql
src/vdk/plugin/impala/templates/load/fact/insert/02-handle-quality-checks.py
src/vdk_impala.egg-info/PKG-INFO
src/vdk_impala.egg-info/SOURCES.txt
src/vdk_impala.egg-info/dependency_links.txt
src/vdk_impala.egg-info/entry_points.txt
src/vdk_impala.egg-info/requires.txt
src/vdk_impala.egg-info/top_level.txt
